javatools/__init__.py
javatools/change.py
javatools/classdiff.py
javatools/classinfo.py
javatools/crypto.py
javatools/dirutils.py
javatools/distdiff.py
javatools/distinfo.py
javatools/jardiff.py
javatools/jarinfo.py
javatools/jarutil.py
javatools/manifest.py
javatools/opcodes.py
javatools/pack.py
javatools/report.py
javatools/ziputils.py
javatools/cheetah/__init__.py
javatools/cheetah/change_Addition.py
javatools/cheetah/change_Addition.tmpl
javatools/cheetah/change_Change.py
javatools/cheetah/change_Change.tmpl
javatools/cheetah/change_Removal.py
javatools/cheetah/change_Removal.tmpl
javatools/cheetah/change_SquashedChange.py
javatools/cheetah/change_SquashedChange.tmpl
javatools/cheetah/change_SuperChange.py
javatools/cheetah/change_SuperChange.tmpl
javatools/cheetah/classdiff_AnnotationsChange.py
javatools/cheetah/classdiff_AnnotationsChange.tmpl
javatools/cheetah/classdiff_ClassConstantPoolChange.py
javatools/cheetah/classdiff_ClassConstantPoolChange.tmpl
javatools/cheetah/classdiff_ClassFieldsChange.py
javatools/cheetah/classdiff_ClassFieldsChange.tmpl
javatools/cheetah/classdiff_ClassInfoChange.py
javatools/cheetah/classdiff_ClassInfoChange.tmpl
javatools/cheetah/classdiff_ClassMethodsChange.py
javatools/cheetah/classdiff_ClassMethodsChange.tmpl
javatools/cheetah/classdiff_FieldChange.py
javatools/cheetah/classdiff_FieldChange.tmpl
javatools/cheetah/classdiff_JavaClassReport.py
javatools/cheetah/classdiff_JavaClassReport.tmpl
javatools/cheetah/classdiff_MethodAdded.py
javatools/cheetah/classdiff_MethodAdded.tmpl
javatools/cheetah/classdiff_MethodChange.py
javatools/cheetah/classdiff_MethodChange.tmpl
javatools/cheetah/classdiff_MethodCodeChange.py
javatools/cheetah/classdiff_MethodCodeChange.tmpl
javatools/cheetah/classdiff_MethodRemoved.py
javatools/cheetah/classdiff_MethodRemoved.tmpl
javatools/cheetah/distdiff_DistClassChange.py
javatools/cheetah/distdiff_DistClassChange.tmpl
javatools/cheetah/distdiff_DistContentChange.py
javatools-1.6.0.dist-info/LICENSE
javatools-1.6.0.dist-info/METADATA
javatools-1.6.0.dist-info/WHEEL
javatools-1.6.0.dist-info/entry_points.txt
javatools-1.6.0.dist-info/top_level.txt
javatools-1.6.0.dist-info/RECORD
