Metadata-Version: 2.1
Name: javatools
Version: 1.6.0
Summary: Tools for working with Java class files and JARs
Home-page: https://github.com/obriencj/python-javatools
Author: Christopher O'Brien
Author-email: obriencj@gmail.com
License: GNU Lesser General Public License v3 (LGPLv3)
Project-URL: Source, https://github.com/obriencj/python-javatools
Project-URL: Bug Reports, https://github.com/obriencj/python-javatools/issues
Platform: any
Classifier: Development Status :: 5 - Production/Stable
Classifier: Environment :: Console
Classifier: Intended Audience :: Developers
Classifier: Intended Audience :: Information Technology
Classifier: License :: OSI Approved :: GNU Lesser General Public License v3 (LGPLv3)
Classifier: Programming Language :: Python :: 2
Classifier: Programming Language :: Python :: 2.7
Classifier: Programming Language :: Python :: 3
Classifier: Programming Language :: Python :: 3.7
Classifier: Programming Language :: Python :: 3.8
Classifier: Programming Language :: Python :: 3.9
Classifier: Programming Language :: Python :: 3.10
Classifier: Programming Language :: Python :: 3.11
Classifier: Topic :: Software Development :: Disassemblers
License-File: LICENSE
Requires-Dist: CT3
Requires-Dist: six
Provides-Extra: crypto
Requires-Dist: M2Crypto (>=0.26.0) ; extra == 'crypto'
